core_commands/__init__.py
core_commands/bash/alias.py
core_commands/bin/__init__.py
core_commands/bin/_validate.py
core_commands/bin/bin.py
core_commands/bin/cmd.py
core_commands/bin/command_list_cmd.py
core_commands/bin/exceptions.py
core_commands/bin/powershell.py
core_commands/bin/shell.py
core_commands/cmd/__init__.py
core_commands/cmd/_creacion.py
core_commands/cmd/_prueba.py
core_commands/cmd/arp.py
core_commands/cmd/assoc.py
core_commands/cmd/attrib.py
core_commands/cmd/auditpol.py
core_commands/cmd/bcdboot.py
core_commands/cmd/bcdedit.py
core_commands/cmd/bitsadmin.py
core_commands/cmd/BREAK.py
core_commands/cmd/cacls.py
core_commands/cmd/call.py
core_commands/cmd/cd.py
core_commands/cmd/certreq.py
core_commands/cmd/certutil.py
core_commands/cmd/change.py
core_commands/cmd/changepk.py
core_commands/cmd/chcp.py
core_commands/cmd/chdir.py
core_commands/cmd/chkdsk.py
core_commands/cmd/chkntfs.py
core_commands/cmd/choice.py
core_commands/cmd/cipher.py
core_commands/cmd/cleanmgr.py
core_commands/cmd/clip.py
core_commands/cmd/cls.py
core_commands/cmd/cmdkey.py
core_commands/cmd/color.py
core_commands/cmd/comp.py
core_commands/cmd/compact.py
core_commands/cmd/convert.py
core_commands/cmd/copy.py
core_commands/cmd/curl.py
core_commands/cmd/date.py
core_commands/cmd/defrag.py
core_commands/cmd/DEL.py
core_commands/cmd/DIR.py
core_commands/cmd/diskpart.py
core_commands/cmd/dism.py
core_commands/cmd/displayswitch.py
core_commands/cmd/doskey.py
core_commands/cmd/driverquery.py
core_commands/cmd/dsregcmd.py
core_commands/cmd/echo.py
core_commands/cmd/endlocal.py
core_commands/cmd/erase.py
core_commands/cmd/esentutl.py
core_commands/cmd/eventcreate.py
core_commands/cmd/EXIT.py
core_commands/cmd/expand.py
core_commands/cmd/explorer.py
core_commands/cmd/fc.py
core_commands/cmd/find.py
core_commands/cmd/findstr.py
core_commands/cmd/fltmc.py
core_commands/cmd/FOR.py
core_commands/cmd/forfiles.py
core_commands/cmd/format.py
core_commands/cmd/fsutil.py
core_commands/cmd/ftp.py
core_commands-1.4.15.dist-info/METADATA
core_commands-1.4.15.dist-info/WHEEL
core_commands-1.4.15.dist-info/RECORD
