Metadata-Version: 2.1
Name: core-commands
Version: 1.4.15
Summary: 
Author: Ricardo Torrellas
Author-email: ricardo.torrejas@gmail.com
Requires-Python: >=3.11,<4.0
Classifier: Programming Language :: Python :: 3
Classifier: Programming Language :: Python :: 3.11
Classifier: Programming Language :: Python :: 3.12
Classifier: Programming Language :: Python :: 3.13
Requires-Dist: core-scripts (>=0.4.3,<0.5.0)
